faker_biology/__init__.py
faker_biology/_utils/parse.py
faker_biology/_utils/parse2.py
faker_biology/bioseq/__init__.py
faker_biology/bioseq/bioseq_data.py
faker_biology/mol_biol/__init__.py
faker_biology/mol_biol/antibody.py
faker_biology/mol_biol/enzyme_data.py
faker_biology/mol_biol/enzymes-raw.wikitext
faker_biology/mol_biol/enzymes.md
faker_biology/mol_biol/re.py
faker_biology/physiology/__init__.py
faker_biology/physiology/cell-types-raw-wiki.txt
faker_biology/physiology/cell-types.md
faker_biology/physiology/celltype_data.py
faker_biology/physiology/organelles.py
faker_biology/physiology/organs_data.py
faker_biology/taxonomy/__init__.py
faker_biology/taxonomy/taxonomy_data.py
faker_biology/tests/__init__.py
faker_biology/tests/test_antibody.py
faker_biology/tests/test_bioseq.py
faker_biology/tests/test_celltypes.py
faker_biology/tests/test_enzymes.py
faker_biology/tests/test_organelles.py
faker_biology/tests/test_organs.py
faker_biology/tests/test_re.py
faker_biology/tests/test_taxonomy.py
faker_biology-0.6.5.dist-info/LICENSE
faker_biology-0.6.5.dist-info/METADATA
faker_biology-0.6.5.dist-info/WHEEL
faker_biology-0.6.5.dist-info/RECORD
