Metadata-Version: 2.1
Name: faker-biology
Version: 0.6.5
Summary: Fake data from biology
Home-page: https://github.com/richarda23/faker-biology
License: Apache 2
Keywords: Biology,Faker
Author: Richard Adams
Author-email: ra22597@gmail.com
Requires-Python: >=3.8,<4.0
Classifier: License :: Other/Proprietary License
Classifier: Programming Language :: Python :: 3
Classifier: Programming Language :: Python :: 3.8
Classifier: Programming Language :: Python :: 3.9
Classifier: Programming Language :: Python :: 3.10
Classifier: Programming Language :: Python :: 3.11
Requires-Dist: Faker (>=12)
Project-URL: Documentation, https://github.com/richarda23/faker-biology
Project-URL: Repository, https://github.com/richarda23/faker-biology
